{"update": "2019-08-19 12:18:14.821271", "calendar": {"2018-07-23": [{"aid": "12569", "name": "Baki (2018) - 5", "kanji": "", "image": "https://img7.anidb.net/pics/anime/thumbs/65x100/221450.jpg-thumb.jpg", "ep": "Still Want to Continue?", "desc": "", "extra": "", "general": ""}, {"aid": "13870", "name": "Cara to Otamajakushi Shima - 14", "kanji": "", "image": "https://img7.anidb.net/pics/anime/thumbs/65x100/214287.jpg-thumb.jpg", "ep": "Episode 14", "desc": "", "extra": "", "general": ""}, {"aid": "13917", "name": "Gintama. (2018) - 3", "kanji": "", "image": "https://img7.anidb.net/pics/anime/thumbs/65x100/221093.jpg-thumb.jpg", "ep": "Making a Dull World Interesting", "desc": "", "extra": "", "general": ""}, {"aid": "13637", "name": "Jashin-chan Dropkick - 3", "kanji": "", "image": "https://img7.anidb.net/pics/anime/thumbs/65x100/221092.jpg-thumb.jpg", "ep": "Episode 3", "desc": "", "extra": "", "general": ""}, {"aid": "13480", "name": "One Room: Second Season - 4", "kanji": "", "image": "https://img7.anidb.net/pics/anime/thumbs/65x100/221082.jpg-thumb.jpg", "ep": "Hanasaka Yui Is Sulking", "desc": "", "extra": "", "general": ""}, {"aid": "13535", "name": "Pittanko!! Nekozakana - 40", "kanji": "", "image": "https://img7.anidb.net/pics/anime/thumbs/65x100/221515.jpg-thumb.jpg", "ep": "Episode 40", "desc": "", "extra": "", "general": ""}, {"aid": "13241", "name": "Shingeki no Kyojin Season 3 - 1", "kanji": "", "image": "https://img7.anidb.net/pics/anime/thumbs/65x100/221456.jpg-thumb.jpg", "ep": "Smoke Signal", "desc": "", "extra": "", "general": ""}, {"aid": "13289", "name": "Yura Yura Suizokukan - 52", "kanji": "", "image": "https://img7.anidb.net/pics/anime/thumbs/65x100/206045.jpg-thumb.jpg", "ep": "Episode 52", "desc": "", "extra": "", "general": ""}], "2018-07-24": [{"aid": "12024", "name": "Asa Da yo! Kai Shain - 576", "kanji": "", "image": "https://img7.anidb.net/pics/anime/thumbs/65x100/184494.jpg-thumb.jpg", "ep": "Episode 576", "desc": "", "extra": "", "general": ""}, {"aid": "13655", "name": "Captain Tsubasa (2018) - 17", "kanji": "", "image": "https://img7.anidb.net/pics/anime/thumbs/65x100/221571.jpg-thumb.jpg", "ep": "Last 4 Minutes! Decisive Battle in the Air", "desc": "", "extra": "", "general": ""}, {"aid": "13859", "name": "Idolmaster Cinderella Girls Gekijou (2018) - 4", "kanji": "", "image": "https://img7.anidb.net/pics/anime/thumbs/65x100/221083.jpg-thumb.jpg", "ep": "Heated Warm Up! / It`s a Special Training / Bling Bling! Cleaning the Pool", "desc": "", "extra": "", "general": ""}, {"aid": "13904", "name": "Kyoto Teramachi Sanjou no Holmes - 3", "kanji": "", "image": "https://img7.anidb.net/pics/anime/thumbs/65x100/221090.jpg-thumb.jpg", "ep": "The Case of the Mt. Kurama Estate Inheritance", "desc": "", "extra": "", "general": ""}, {"aid": "14008", "name": "Overlord III - S3", "kanji": "", "image": "https://img7.anidb.net/pics/anime/thumbs/65x100/221902.jpg-thumb.jpg", "ep": "Ple-Ple-Pleiades 3: Ple 3 Ch 3 &quot;His Distant and Worrying Delicate Status&quot;", "desc": "", "extra": "", "general": ""}, {"aid": "13960", "name": "Senjuushi - 4", "kanji": "", "image": "https://img7.anidb.net/pics/anime/thumbs/65x100/221081.jpg-thumb.jpg", "ep": "Town", "desc": "", "extra": "", "general": ""}, {"aid": "13205", "name": "Yama no Susume: Third Season - 4", "kanji": "", "image": "https://img7.anidb.net/pics/anime/thumbs/65x100/221079.jpg-thumb.jpg", "ep": "Having Fun with Classmates!", "desc": "", "extra": "", "general": ""}], "2018-07-25": [{"aid": "12024", "name": "Asa Da yo! Kai Shain - 577", "kanji": "", "image": "https://img7.anidb.net/pics/anime/thumbs/65x100/184494.jpg-thumb.jpg", "ep": "Episode 577", "desc": "", "extra": "", "general": ""}, {"aid": "14028", "name": "Baiye Linglong - 8", "kanji": "", "image": "https://img7.anidb.net/pics/anime/thumbs/65x100/219159.jpg-thumb.jpg", "ep": "Episode 8", "desc": "", "extra": "", "general": ""}, {"aid": "14099", "name": "Huan Jie Wang - 9", "kanji": "", "image": "https://img7.anidb.net/pics/anime/thumbs/65x100/230030.jpg-thumb.jpg", "ep": "Episode 9", "desc": "", "extra": "", "general": ""}, {"aid": "13266", "name": "Lupin Sansei: Part 5 - 16", "kanji": "", "image": "https://img7.anidb.net/pics/anime/thumbs/65x100/221781.jpg-thumb.jpg", "ep": "Let`s Talk About First Loves", "desc": "", "extra": "", "general": ""}, {"aid": "12942", "name": "Mahou Tsukai no Yome - S31", "kanji": "", "image": "https://img7.anidb.net/pics/anime/thumbs/65x100/221983.jpg-thumb.jpg", "ep": "Special Event", "desc": "", "extra": "", "general": ""}, {"aid": "13426", "name": "Uchuu Senkan Tiramisu - S3", "kanji": "", "image": "https://img7.anidb.net/pics/anime/thumbs/65x100/221692.jpg-thumb.jpg", "ep": "0203", "desc": "", "extra": "", "general": ""}, {"aid": "14191", "name": "Yin Yang Shi: Ping An Wu Yu - 4", "kanji": "", "image": "https://img7.anidb.net/pics/anime/thumbs/65x100/221864.jpg-thumb.jpg", "ep": "Episode 4", "desc": "", "extra": "", "general": ""}, {"aid": "12659", "name": "Yuu Gi Ou: Vrains - 61", "kanji": "", "image": "https://img7.anidb.net/pics/anime/thumbs/65x100/198634.jpg-thumb.jpg", "ep": "Despair from Darkness", "desc": "", "extra": "", "general": ""}], "2018-07-26": [{"aid": "12024", "name": "Asa Da yo! Kai Shain - 578", "kanji": "", "image": "https://img7.anidb.net/pics/anime/thumbs/65x100/184494.jpg-thumb.jpg", "ep": "Episode 578", "desc": "", "extra": "", "general": ""}, {"aid": "12661", "name": "Boruto: Naruto Next Generations - 66", "kanji": "", "image": "https://img7.anidb.net/pics/anime/thumbs/65x100/198901.jpg-thumb.jpg", "ep": "My Story...!", "desc": "", "extra": "", "general": ""}, {"aid": "14114", "name": "Ice Kuritarou - 40", "kanji": "", "image": "https://img7.anidb.net/pics/anime/thumbs/65x100/66124.png-thumb.jpg", "ep": "Episode 40", "desc": "", "extra": "", "general": ""}, {"aid": "14377", "name": "Jiyi U Pan - 3", "kanji": "", "image": "https://img7.anidb.net/pics/anime/thumbs/65x100/223174.jpg-thumb.jpg", "ep": "Episode 3", "desc": "", "extra": "", "general": ""}, {"aid": "14375", "name": "Moshi Juexing Zhi Ruqin - 11", "kanji": "", "image": "https://img7.anidb.net/pics/anime/thumbs/65x100/223172.jpg-thumb.jpg", "ep": "Episode 11", "desc": "", "extra": "", "general": ""}, {"aid": "14052", "name": "Okojo to Yamane - 2", "kanji": "", "image": "https://img7.anidb.net/pics/anime/thumbs/65x100/216639.jpg-thumb.jpg", "ep": "Episode 2", "desc": "", "extra": "", "general": ""}, {"aid": "10816", "name": "Overlord - S12", "kanji": "", "image": "https://img7.anidb.net/pics/anime/thumbs/65x100/224772.jpg-thumb.jpg", "ep": "Table Game to Understand Humans", "desc": "", "extra": "", "general": ""}, {"aid": "12407", "name": "Pocket Monsters Sun & Moon - 83", "kanji": "", "image": "https://img7.anidb.net/pics/anime/thumbs/65x100/231551.jpg-thumb.jpg", "ep": "Dummy, You Shrunk the Kids!", "desc": "", "extra": "", "general": ""}, {"aid": "13959", "name": "Sirius the Jaeger - 3", "kanji": "", "image": "https://img7.anidb.net/pics/anime/thumbs/65x100/221120.jpg-thumb.jpg", "ep": "Indelible Memories", "desc": "", "extra": "", "general": ""}, {"aid": "13589", "name": "Sunohara-sou no Kanrinin-san - 4", "kanji": "", "image": "https://img7.anidb.net/pics/anime/thumbs/65x100/221073.jpg-thumb.jpg", "ep": "Start of the Rainy Season, Weddings, Lap Pillow", "desc": "", "extra": "", "general": ""}, {"aid": "13855", "name": "Usagi no Mathew - 17", "kanji": "", "image": "https://img7.anidb.net/pics/anime/thumbs/65x100/213937.jpg-thumb.jpg", "ep": "Episode 17", "desc": "", "extra": "", "general": ""}, {"aid": "12362", "name": "Yume Oukoku to Nemureru 100 Nin no Ouji-sama - 4", "kanji": "", "image": "https://img7.anidb.net/pics/anime/thumbs/65x100/218947.jpg-thumb.jpg", "ep": "The Pirate Ship Barenarossa", "desc": "", "extra": "", "general": ""}], "2018-07-27": [{"aid": "13613", "name": "Akkun to Kanojo - 17", "kanji": "", "image": "https://img7.anidb.net/pics/anime/thumbs/65x100/213018.jpg-thumb.jpg", "ep": "Akkun`s Sleepover", "desc": "", "extra": "", "general": ""}, {"aid": "13536", "name": "Banana Fish - 4", "kanji": "", "image": "https://img7.anidb.net/pics/anime/thumbs/65x100/221076.jpg-thumb.jpg", "ep": "This Side of Paradise", "desc": "", "extra": "", "general": ""}, {"aid": "12283", "name": "Bikini Warriors (2016) - 5", "kanji": "", "image": "https://img7.anidb.net/pics/anime/thumbs/65x100/189141.jpg-thumb.jpg", "ep": "Bikini of the Dead", "desc": "", "extra": "", "general": ""}, {"aid": "14128", "name": "Caramel Honey - 22", "kanji": "", "image": "https://img7.anidb.net/pics/anime/thumbs/65x100/221466.jpg-thumb.jpg", "ep": "Episode 22", "desc": "", "extra": "", "general": ""}, {"aid": "13250", "name": "Chio-chan no Tsuugakuro - 4", "kanji": "", "image": "https://img7.anidb.net/pics/anime/thumbs/65x100/221084.jpg-thumb.jpg", "ep": "Smoke on the Sailor / Taking the Cherry Blossom in Your Hand / Manana`s School Road", "desc": "", "extra": "", "general": ""}, {"aid": "4635", "name": "Doraemon (2005) - 452", "kanji": "", "image": "https://img7.anidb.net/pics/anime/thumbs/65x100/2381.gif-thumb.jpg", "ep": "Episode 452", "desc": "", "extra": "", "general": ""}, {"aid": "14228", "name": "Dot Bit Retro: Boku Dake no Kusogee - 6", "kanji": "", "image": "https://img7.anidb.net/pics/anime/thumbs/65x100/221497.jpg-thumb.jpg", "ep": "Episode 6", "desc": "", "extra": "", "general": ""}, {"aid": "13995", "name": "Hataraku Onii-san! No 2! - 3", "kanji": "", "image": "https://img7.anidb.net/pics/anime/thumbs/65x100/215626.jpg-thumb.jpg", "ep": "Cafe Buddies!", "desc": "", "extra": "", "general": ""}, {"aid": "13840", "name": "Masamune-kun no Revenge (2018)", "kanji": "", "image": "https://img7.anidb.net/pics/anime/thumbs/65x100/223396.jpg-thumb.jpg", "ep": "OAD", "desc": "", "extra": "", "general": ""}, {"aid": "13778", "name": "Moshimoshi, Terumi Desu. - 21", "kanji": "", "image": "https://img7.anidb.net/pics/anime/thumbs/65x100/221465.jpg-thumb.jpg", "ep": "Episode 21", "desc": "", "extra": "", "general": ""}, {"aid": "14206", "name": "Nekopara: Koneko no Hi no Yakusoku", "kanji": "", "image": "https://img7.anidb.net/pics/anime/thumbs/65x100/221540.jpg-thumb.jpg", "ep": "Web", "desc": "", "extra": "", "general": ""}, {"aid": "13307", "name": "Satsuriku no Tenshi - 4", "kanji": "", "image": "https://img7.anidb.net/pics/anime/thumbs/65x100/221071.jpg-thumb.jpg", "ep": "A Sinner Has No Right of Choice.", "desc": "", "extra": "", "general": ""}, {"aid": "13152", "name": "Shoujo Kageki Revue Starlight - 3", "kanji": "", "image": "https://img7.anidb.net/pics/anime/thumbs/65x100/218686.jpg-thumb.jpg", "ep": "Top Star", "desc": "", "extra": "", "general": ""}, {"aid": "14505", "name": "TV Yarou Nanana - 17", "kanji": "", "image": "https://img7.anidb.net/pics/anime/thumbs/65x100/227154.jpg-thumb.jpg", "ep": "Showdown! Banana Champion", "desc": "", "extra": "", "general": ""}, {"aid": "12945", "name": "Yankee Hamster - 102", "kanji": "", "image": "https://img7.anidb.net/pics/anime/thumbs/65x100/199361.jpg-thumb.jpg", "ep": "Episode 102", "desc": "", "extra": "", "general": ""}, {"aid": "13807", "name": "Youkai Watch: Shadow Side - 17", "kanji": "", "image": "https://img7.anidb.net/pics/anime/thumbs/65x100/213017.jpg-thumb.jpg", "ep": "Episode 17", "desc": "", "extra": "", "general": ""}], "2018-07-28": [{"aid": "13635", "name": "Cardfight!! Vanguard (2018) - 13", "kanji": "", "image": "https://img7.anidb.net/pics/anime/thumbs/65x100/214803.jpg-thumb.jpg", "ep": "Kamui!! Revenge of Determination", "desc": "", "extra": "", "general": ""}, {"aid": "13734", "name": "Grand Blue - 3", "kanji": "", "image": "https://img7.anidb.net/pics/anime/thumbs/65x100/221461.jpg-thumb.jpg", "ep": "A New World", "desc": "", "extra": "", "general": ""}, {"aid": "14216", "name": "Hawaiian Conu - 4", "kanji": "", "image": "https://img7.anidb.net/pics/anime/thumbs/65x100/220332.jpg-thumb.jpg", "ep": "Episode 4", "desc": "", "extra": "", "general": ""}, {"aid": "13698", "name": "Iya na Kao Sarenagara Opantsu Misete Moraitai - 3", "kanji": "", "image": "https://img7.anidb.net/pics/anime/thumbs/65x100/221602.jpg-thumb.jpg", "ep": "Episode 3", "desc": "", "extra": "", "general": ""}, {"aid": "13518", "name": "Major 2nd - 17", "kanji": "", "image": "https://img7.anidb.net/pics/anime/thumbs/65x100/212070.jpg-thumb.jpg", "ep": "I Don`t Want to Lose", "desc": "", "extra": "", "general": ""}, {"aid": "14287", "name": "Meng Ta: Xue Mi Cheng - 10", "kanji": "", "image": "https://img7.anidb.net/pics/anime/thumbs/65x100/222308.jpg-thumb.jpg", "ep": "Episode 10", "desc": "", "extra": "", "general": ""}, {"aid": "14183", "name": "Monster Strike The Animation - 4", "kanji": "", "image": "https://img7.anidb.net/pics/anime/thumbs/65x100/219516.jpg-thumb.jpg", "ep": "Behold, I Am King Grouch!", "desc": "", "extra": "", "general": ""}, {"aid": "13811", "name": "Oshiete Mahou no Pendulum: Rilu Rilu Fairilu - 4", "kanji": "", "image": "https://img7.anidb.net/pics/anime/thumbs/65x100/221097.jpg-thumb.jpg", "ep": "Episode 4", "desc": "", "extra": "", "general": ""}, {"aid": "13514", "name": "Pochitto Hatsumei: Pikachin-Kit - 30", "kanji": "", "image": "https://img7.anidb.net/pics/anime/thumbs/65x100/224011.jpg-thumb.jpg", "ep": "Episode 30", "desc": "", "extra": "", "general": ""}, {"aid": "13507", "name": "Shinkansen Henkei Robo Shinkalion the Animation - 29", "kanji": "", "image": "https://img7.anidb.net/pics/anime/thumbs/65x100/221625.jpg-thumb.jpg", "ep": "To the Sea!! Investigate the Enemy Signal", "desc": "", "extra": "", "general": ""}, {"aid": "13552", "name": "Yuragi-sou no Yuuna-san - 3", "kanji": "", "image": "https://img7.anidb.net/pics/anime/thumbs/65x100/221126.jpg-thumb.jpg", "ep": "Yuuna Goes to School", "desc": "", "extra": "", "general": ""}, {"aid": "13845", "name": "Zoids Wild - 4", "kanji": "", "image": "https://img7.anidb.net/pics/anime/thumbs/65x100/213663.jpg-thumb.jpg", "ep": "Mighty Foes! Death Metal`s Elite Four", "desc": "", "extra": "", "general": ""}], "2018-07-29": [{"aid": "1842", "name": "Chibi Maruko-chan (1995) - 1163", "kanji": "", "image": "https://img7.anidb.net/pics/anime/thumbs/65x100/2595.jpg-thumb.jpg", "ep": "Episode 1163", "desc": "", "extra": "", "general": ""}, {"aid": "12046", "name": "Fate/Extra: Last Encore - 11", "kanji": "", "image": "https://img7.anidb.net/pics/anime/thumbs/65x100/221978.jpg-thumb.jpg", "ep": "Resurrected Sword of Victory: Excalibur Galatine", "desc": "", "extra": "", "general": ""}, {"aid": "12046", "name": "Fate/Extra: Last Encore - 13", "kanji": "", "image": "https://img7.anidb.net/pics/anime/thumbs/65x100/221978.jpg-thumb.jpg", "ep": "The Applauding Rose: Olympia Plaudere", "desc": "", "extra": "", "general": ""}, {"aid": "14159", "name": "Guan Hai Ce - 7", "kanji": "", "image": "https://img7.anidb.net/pics/anime/thumbs/65x100/219158.jpg-thumb.jpg", "ep": "Episode 7", "desc": "", "extra": "", "general": ""}, {"aid": "13526", "name": "Hugtto! Precure - 26", "kanji": "", "image": "https://img7.anidb.net/pics/anime/thumbs/65x100/211273.jpg-thumb.jpg", "ep": "Up-Close with the Superstar Actress! Saaya and Her Mother", "desc": "", "extra": "", "general": ""}, {"aid": "12020", "name": "Island - 5", "kanji": "", "image": "https://img7.anidb.net/pics/anime/thumbs/65x100/221263.jpg-thumb.jpg", "ep": "That`s Why I Trust You", "desc": "", "extra": "", "general": ""}, {"aid": "13488", "name": "Koneko no Chii: Ponponraa Dairyokou - 16", "kanji": "", "image": "https://img7.anidb.net/pics/anime/thumbs/65x100/221441.jpg-thumb.jpg", "ep": "Come-Come Climbs a Mountain", "desc": "", "extra": "", "general": ""}, {"aid": "69", "name": "One Piece - 847", "kanji": "", "image": "https://img7.anidb.net/pics/anime/thumbs/65x100/224210.jpg-thumb.jpg", "ep": "A Coincidental Reunion! Sanji and the Lovestruck Evil Pudding!", "desc": "", "extra": "", "general": ""}, {"aid": "13965", "name": "Planet With - 4", "kanji": "", "image": "https://img7.anidb.net/pics/anime/thumbs/65x100/224519.jpg-thumb.jpg", "ep": "Avenger 2", "desc": "", "extra": "", "general": ""}, {"aid": "1830", "name": "Sazae-san - 2456", "kanji": "", "image": "https://img7.anidb.net/pics/anime/thumbs/65x100/73013.jpg-thumb.jpg", "ep": "Episode 2456", "desc": "", "extra": "", "general": ""}, {"aid": "13875", "name": "Wakaokami wa Shougakusei! - 16", "kanji": "", "image": "https://img7.anidb.net/pics/anime/thumbs/65x100/221872.jpg-thumb.jpg", "ep": "The Young Innkeeper and the Reason Behind the Tears!", "desc": "", "extra": "", "general": ""}]}}