{"update": "2020-10-23 11:44:56.030777", "calendar": {"2020-11-23": [{"aid": "15759", "name": "Himitsukessha Taka no Tsume: Golden Spell - 8", "kanji": "", "image": "https://cdn-eu.anidb.net/images/65x100/252702.jpg-thumb.jpg", "ep": "Episode 8", "desc": "", "extra": "", "general": ""}, {"aid": "15697", "name": "Otona Nya Koi no Shikata ga Wakaranee! - 8", "kanji": "", "image": "https://cdn-eu.anidb.net/images/65x100/251525.jpg-thumb.jpg", "ep": "Episode 8", "desc": "", "extra": "", "general": ""}], "2020-11-24": [{"aid": "15411", "name": "One Room: Third Season - 8", "kanji": "", "image": "https://cdn-eu.anidb.net/images/65x100/251962.jpg-thumb.jpg", "ep": "Episode 8", "desc": "", "extra": "", "general": ""}, {"aid": "15134", "name": "Shadowverse - 32", "kanji": "", "image": "https://cdn-eu.anidb.net/images/65x100/244982.jpg-thumb.jpg", "ep": "Episode 32", "desc": "", "extra": "", "general": ""}], "2020-11-25": [{"aid": "14485", "name": "Tsukiuta. The Animation 2 - 8", "kanji": "", "image": "https://cdn-eu.anidb.net/images/65x100/252776.jpg-thumb.jpg", "ep": "Episode 8", "desc": "", "extra": "", "general": ""}], "2020-11-26": [{"aid": "15409", "name": "Noblesse - 8", "kanji": "", "image": "https://cdn-eu.anidb.net/images/65x100/252044.jpg-thumb.jpg", "ep": "Episode 8", "desc": "", "extra": "", "general": ""}], "2020-11-27": [{"aid": "15368", "name": "Battle Spirits: Kakumei no Galette - 3", "kanji": "", "image": "https://cdn-eu.anidb.net/images/65x100/251186.jpg-thumb.jpg", "ep": "Episode 3", "desc": "", "extra": "", "general": ""}, {"aid": "15414", "name": "Kimi wa Kanata", "kanji": "", "image": "https://cdn-eu.anidb.net/images/65x100/250054.jpg-thumb.jpg", "ep": "Complete Movie", "desc": "", "extra": "", "general": ""}, {"aid": "14526", "name": "Tensei Shitara Slime Datta Ken (2019) - 5", "kanji": "", "image": "https://cdn-eu.anidb.net/images/65x100/241520.jpg-thumb.jpg", "ep": "OAD 5", "desc": "", "extra": "", "general": ""}], "2020-11-29": [{"aid": "15318", "name": "Toji no Miko: Kizamishi Issen no Tomoshibi - 2", "kanji": "", "image": "https://cdn-eu.anidb.net/images/65x100/249063.jpg-thumb.jpg", "ep": "Volume 2", "desc": "", "extra": "", "general": ""}]}}