{"update": "2021-10-30 00:49:50.846766", "calendar": {"2021-06-07": [{"aid": "15332", "name": "Hige o Soru. Soshite Joshikousei o Hirou. - 10", "kanji": "", "image": "https://cdn-eu.anidb.net/images/65/259935.jpg-thumb.jpg", "ep": "Proof", "desc": "", "extra": "", "general": ""}, {"aid": "15259", "name": "Kingdom (2020) - 10", "kanji": "", "image": "https://cdn-eu.anidb.net/images/65/261057.jpg-thumb.jpg", "ep": "A Promotion in a Predicament", "desc": "", "extra": "", "general": ""}, {"aid": "16199", "name": "Koko Animal Otogibanashi - 8", "kanji": "", "image": "https://cdn-eu.anidb.net/images/65/259715.jpg-thumb.jpg", "ep": "Episode 8", "desc": "", "extra": "", "general": ""}, {"aid": "16454", "name": "Washimo (2021) - 20", "kanji": "", "image": "https://cdn-eu.anidb.net/images/65/265595.jpg-thumb.jpg", "ep": "Episode 20", "desc": "", "extra": "", "general": ""}, {"aid": "16688", "name": "Wo Zhen Di Meiyong Mie? - 8", "kanji": "", "image": "https://cdn-eu.anidb.net/images/65/265086.jpg-thumb.jpg", "ep": "Episode 8", "desc": "", "extra": "", "general": ""}, {"aid": "15660", "name": "Yakunara Mug Cup mo - 10", "kanji": "", "image": "https://cdn-eu.anidb.net/images/65/258511.jpg-thumb.jpg", "ep": "Hime-chan Is Doing Her Best", "desc": "", "extra": "", "general": ""}, {"aid": "15660", "name": "Yakunara Mug Cup mo - S11", "kanji": "", "image": "https://cdn-eu.anidb.net/images/65/258511.jpg-thumb.jpg", "ep": "After School of Yakumo 10", "desc": "", "extra": "", "general": ""}], "2021-06-08": [{"aid": "15608", "name": "Fushigi Dagashiya: Zenitendou - 28", "kanji": "", "image": "https://cdn-eu.anidb.net/images/65/259191.jpg-thumb.jpg", "ep": "Episode 28", "desc": "", "extra": "", "general": ""}, {"aid": "16675", "name": "Li Lin Ke Di: Xiao Guan Ren - 8", "kanji": "", "image": "https://cdn-eu.anidb.net/images/65/265037.jpg-thumb.jpg", "ep": "Episode 8", "desc": "", "extra": "", "general": ""}, {"aid": "16517", "name": "Moshi Juexing: Suyuan Xupian - 9", "kanji": "", "image": "https://cdn-eu.anidb.net/images/65/263707.jpg-thumb.jpg", "ep": "Episode 9", "desc": "", "extra": "", "general": ""}, {"aid": "15720", "name": "Seijo no Maryoku wa Bannou Desu - 10", "kanji": "", "image": "https://cdn-eu.anidb.net/images/65/255061.jpg-thumb.jpg", "ep": "Diary", "desc": "", "extra": "", "general": ""}, {"aid": "16396", "name": "Wan Jie Duzun - 21", "kanji": "", "image": "https://cdn-eu.anidb.net/images/65/261619.jpg-thumb.jpg", "ep": "Episode 21", "desc": "", "extra": "", "general": ""}, {"aid": "16676", "name": "Yi Shijie Zhongyao Pu (2021) - 16", "kanji": "", "image": "https://cdn-eu.anidb.net/images/65/10811.jpeg-thumb.jpg", "ep": "Episode 16", "desc": "", "extra": "", "general": ""}], "2021-06-09": [{"aid": "15493", "name": "Isekai Maou to Shoukan Shoujo no Dorei Majutsu Omega - S19", "kanji": "", "image": "https://cdn-eu.anidb.net/images/65/258325.jpg-thumb.jpg", "ep": "Mini Anime 17", "desc": "", "extra": "", "general": ""}, {"aid": "16612", "name": "Jueshi Wu Hun - 69", "kanji": "", "image": "https://cdn-eu.anidb.net/images/65/265245.jpg-thumb.jpg", "ep": "Episode 69", "desc": "", "extra": "", "general": ""}, {"aid": "15905", "name": "Kyuukyoku Shinka Shita Full Dive RPG ga Genjitsu yori mo Kusogee Dattara - 10", "kanji": "", "image": "https://cdn-eu.anidb.net/images/65/262164.jpg-thumb.jpg", "ep": "A New Ally", "desc": "", "extra": "", "general": ""}, {"aid": "15756", "name": "Osananajimi ga Zettai ni Makenai LoveCome - 9", "kanji": "", "image": "https://cdn-eu.anidb.net/images/65/258181.jpg-thumb.jpg", "ep": "Paradise SOS", "desc": "", "extra": "", "general": ""}, {"aid": "15260", "name": "Super Cub - 10", "kanji": "", "image": "https://cdn-eu.anidb.net/images/65/255766.jpg-thumb.jpg", "ep": "Snow", "desc": "", "extra": "", "general": ""}, {"aid": "16438", "name": "Xing Hai Qishi: Xia Ban Ji - 4", "kanji": "", "image": "https://cdn-eu.anidb.net/images/65/262790.jpg-thumb.jpg", "ep": "Episode 4", "desc": "", "extra": "", "general": ""}, {"aid": "16493", "name": "Xixing Ji: Suming Pian - 6", "kanji": "", "image": "https://cdn-eu.anidb.net/images/65/263704.jpg-thumb.jpg", "ep": "Episode 6", "desc": "", "extra": "", "general": ""}, {"aid": "15693", "name": "Yi Nian Yong Heng - 46", "kanji": "", "image": "https://cdn-eu.anidb.net/images/65/251380.jpg-thumb.jpg", "ep": "Episode 46", "desc": "", "extra": "", "general": ""}], "2021-06-10": [{"aid": "15770", "name": "Godzilla S.P - 12", "kanji": "", "image": "https://cdn-eu.anidb.net/images/65/258309.jpg-thumb.jpg", "ep": "Explorer / The End of the Fight", "desc": "", "extra": "", "general": ""}, {"aid": "16314", "name": "Hua Jianghu: Buliang Ren IV - 9", "kanji": "", "image": "https://cdn-eu.anidb.net/images/65/260585.jpg-thumb.jpg", "ep": "Episode 9", "desc": "", "extra": "", "general": ""}, {"aid": "16510", "name": "Kaijuu Step SDGs Daisakusen - 15", "kanji": "", "image": "https://cdn-eu.anidb.net/images/65/263553.jpg-thumb.jpg", "ep": "Episode 15", "desc": "", "extra": "", "general": ""}, {"aid": "16674", "name": "Kuang Shen Mo Zun - 15", "kanji": "", "image": "https://cdn-eu.anidb.net/images/65/265035.jpg-thumb.jpg", "ep": "Episode 15", "desc": "", "extra": "", "general": ""}, {"aid": "16687", "name": "Luo Xiao Hei Zhanji (2021) - 11", "kanji": "", "image": "https://cdn-eu.anidb.net/images/65/265084.jpg-thumb.jpg", "ep": "Episode 11", "desc": "", "extra": "", "general": ""}, {"aid": "15849", "name": "SD Gundam World Heroes - 10", "kanji": "", "image": "https://cdn-eu.anidb.net/images/65/260766.jpg-thumb.jpg", "ep": "Sneak In! The Night Museum", "desc": "", "extra": "", "general": ""}, {"aid": "16354", "name": "Shi Yi ChangAn: Mingyue Jishi You Er - 10", "kanji": "", "image": "https://cdn-eu.anidb.net/images/65/260929.jpg-thumb.jpg", "ep": "Episode 10", "desc": "", "extra": "", "general": ""}, {"aid": "16585", "name": "Wei Wo Du Shen - 39", "kanji": "", "image": "https://cdn-eu.anidb.net/images/65/264559.jpg-thumb.jpg", "ep": "Episode 39", "desc": "", "extra": "", "general": ""}, {"aid": "15028", "name": "Zombie Land Saga Revenge - 10", "kanji": "", "image": "https://cdn-eu.anidb.net/images/65/255162.jpg-thumb.jpg", "ep": "The Saga of How These Zombies Will Get Their Revenge", "desc": "", "extra": "", "general": ""}, {"aid": "15028", "name": "Zombie Land Saga Revenge - S1", "kanji": "", "image": "https://cdn-eu.anidb.net/images/65/255162.jpg-thumb.jpg", "ep": "Dig Here, Zom Zom! Episode 10 Pre-Broadcast Special", "desc": "", "extra": "", "general": ""}], "2021-06-11": [{"aid": "16830", "name": "Bai Gui Youeryuan Di Si Ji - 3", "kanji": "", "image": "https://cdn-eu.anidb.net/images/65/265766.jpg-thumb.jpg", "ep": "Episode 3", "desc": "", "extra": "", "general": ""}, {"aid": "16126", "name": "Beyblade Burst Dynamite Battle - 12", "kanji": "", "image": "https://cdn-eu.anidb.net/images/65/258510.jpg-thumb.jpg", "ep": "Belial`s Upgrade!!", "desc": "", "extra": "", "general": ""}, {"aid": "15963", "name": "Gyokou no Nikuko-chan", "kanji": "", "image": "https://cdn-eu.anidb.net/images/65/261060.jpg-thumb.jpg", "ep": "Complete Movie", "desc": "", "extra": "", "general": ""}, {"aid": "15493", "name": "Isekai Maou to Shoukan Shoujo no Dorei Majutsu Omega - 10", "kanji": "", "image": "https://cdn-eu.anidb.net/images/65/258325.jpg-thumb.jpg", "ep": "Pretend God", "desc": "", "extra": "", "general": ""}, {"aid": "15925", "name": "Kintamani Dog - 22", "kanji": "", "image": "https://cdn-eu.anidb.net/images/65/254901.jpg-thumb.jpg", "ep": "Episode 22", "desc": "", "extra": "", "general": ""}, {"aid": "16269", "name": "Mi Bao Zhi Guo - 10", "kanji": "", "image": "https://cdn-eu.anidb.net/images/65/260181.jpg-thumb.jpg", "ep": "Episode 10", "desc": "", "extra": "", "general": ""}, {"aid": "15067", "name": "Pocket Monsters (2019) - 70", "kanji": "", "image": "https://cdn-eu.anidb.net/images/65/240961.jpg-thumb.jpg", "ep": "Please! Get Morpeko!!", "desc": "", "extra": "", "general": ""}, {"aid": "15312", "name": "SSSS.Dynazenon - 11", "kanji": "", "image": "https://cdn-eu.anidb.net/images/65/258902.jpg-thumb.jpg", "ep": "What Wish Can`t Come True?", "desc": "", "extra": "", "general": ""}, {"aid": "15994", "name": "Shinkansen Henkei Robo Shinkalion Z the Animation - 10", "kanji": "", "image": "https://cdn-eu.anidb.net/images/65/259118.jpg-thumb.jpg", "ep": "The Great Aerial Battle! A Turbulent Z Combination!!", "desc": "", "extra": "", "general": ""}, {"aid": "16397", "name": "Wushang Shen Di Di Er Ji - 9", "kanji": "", "image": "https://cdn-eu.anidb.net/images/65/261621.jpg-thumb.jpg", "ep": "Episode 9", "desc": "", "extra": "", "general": ""}, {"aid": "16077", "name": "Youkai Watch (2021) - 10", "kanji": "", "image": "https://cdn-eu.anidb.net/images/65/260077.jpg-thumb.jpg", "ep": "Episode 10", "desc": "", "extra": "", "general": ""}], "2021-06-12": [{"aid": "15341", "name": "Back Arrow - 23", "kanji": "", "image": "https://cdn-eu.anidb.net/images/65/254852.jpg-thumb.jpg", "ep": "Does Destruction Rain from the Heavens?", "desc": "", "extra": "", "general": ""}, {"aid": "15484", "name": "Boku no Hero Academia (2021) - 12", "kanji": "", "image": "https://cdn-eu.anidb.net/images/65/257382.jpg-thumb.jpg", "ep": "The New Power and All for One", "desc": "", "extra": "", "general": ""}, {"aid": "15646", "name": "Cardfight!! Vanguard: Over Dress - 10", "kanji": "", "image": "https://cdn-eu.anidb.net/images/65/258847.jpg-thumb.jpg", "ep": "Fluttering Banner", "desc": "", "extra": "", "general": ""}, {"aid": "4635", "name": "Doraemon (2005) - 573", "kanji": "", "image": "https://cdn-eu.anidb.net/images/65/2381.gif-thumb.jpg", "ep": "Episode 573", "desc": "", "extra": "", "general": ""}, {"aid": "15321", "name": "Dragon Quest: Dai no Daibouken (2020) - 36", "kanji": "", "image": "https://cdn-eu.anidb.net/images/65/251007.jpg-thumb.jpg", "ep": "The Superior Being Versus Chiu", "desc": "", "extra": "", "general": ""}, {"aid": "16046", "name": "Inou no Aicis: ESP & High School Detective - 15", "kanji": "", "image": "https://cdn-eu.anidb.net/images/65/256991.jpg-thumb.jpg", "ep": "Episode 15", "desc": "", "extra": "", "general": ""}, {"aid": "16674", "name": "Kuang Shen Mo Zun - 16", "kanji": "", "image": "https://cdn-eu.anidb.net/images/65/265035.jpg-thumb.jpg", "ep": "Episode 16", "desc": "", "extra": "", "general": ""}, {"aid": "15428", "name": "Mairimashita! Iruma-kun (2021) - 9", "kanji": "", "image": "https://cdn-eu.anidb.net/images/65/262161.jpg-thumb.jpg", "ep": "Studying in the Netherworld", "desc": "", "extra": "", "general": ""}, {"aid": "266", "name": "Meitantei Conan - 1008", "kanji": "", "image": "https://cdn-eu.anidb.net/images/65/58683.jpg-thumb.jpg", "ep": "Out for Revenge (Part 2)", "desc": "", "extra": "", "general": ""}, {"aid": "15628", "name": "Shakunetsu Kabaddi - 11", "kanji": "", "image": "https://cdn-eu.anidb.net/images/65/258563.jpg-thumb.jpg", "ep": "The Direction We`re Aiming", "desc": "", "extra": "", "general": ""}, {"aid": "15994", "name": "Shinkansen Henkei Robo Shinkalion Z the Animation - S1", "kanji": "", "image": "https://cdn-eu.anidb.net/images/65/259118.jpg-thumb.jpg", "ep": "Episode S1", "desc": "", "extra": "", "general": ""}, {"aid": "15201", "name": "Slime Taoshite 300-nen, Shiranai Uchi ni Level Max ni Nattemashita - S2", "kanji": "", "image": "https://cdn-eu.anidb.net/images/65/257444.jpg-thumb.jpg", "ep": "Episode S2", "desc": "", "extra": "", "general": ""}, {"aid": "14556", "name": "Thunderbolt Fantasy: Touri-ken Yuuki 3 - 11", "kanji": "", "image": "https://cdn-eu.anidb.net/images/65/259996.jpg-thumb.jpg", "ep": "Distant Song", "desc": "", "extra": "", "general": ""}, {"aid": "16396", "name": "Wan Jie Duzun - 22", "kanji": "", "image": "https://cdn-eu.anidb.net/images/65/261619.jpg-thumb.jpg", "ep": "Episode 22", "desc": "", "extra": "", "general": ""}, {"aid": "15577", "name": "Yuuki Yuuna wa Yuusha de Aru Churutto! - 10", "kanji": "", "image": "https://cdn-eu.anidb.net/images/65/258398.jpg-thumb.jpg", "ep": "Episode 10", "desc": "", "extra": "", "general": ""}], "2021-06-13": [{"aid": "15612", "name": "Battle Athletess Daiundoukai Restart! - 10", "kanji": "", "image": "https://cdn-eu.anidb.net/images/65/254907.jpg-thumb.jpg", "ep": "A World Out of Reach", "desc": "", "extra": "", "general": ""}, {"aid": "12661", "name": "Boruto: Naruto Next Generations - 203", "kanji": "", "image": "https://cdn-eu.anidb.net/images/65/258555.jpg-thumb.jpg", "ep": "Surprise Attack!", "desc": "", "extra": "", "general": ""}, {"aid": "16192", "name": "Daomu Biji: Qinling Shen Shu - 12", "kanji": "", "image": "https://cdn-eu.anidb.net/images/65/259616.jpg-thumb.jpg", "ep": "Episode 12", "desc": "", "extra": "", "general": ""}, {"aid": "15962", "name": "Dinosaur Biyori - 11", "kanji": "", "image": "https://cdn-eu.anidb.net/images/65/255170.jpg-thumb.jpg", "ep": "Episode 11", "desc": "", "extra": "", "general": ""}, {"aid": "15142", "name": "Dragon, Ie o Kau. - 11", "kanji": "", "image": "https://cdn-eu.anidb.net/images/65/258369.jpg-thumb.jpg", "ep": "A Home for a Kingdom", "desc": "", "extra": "", "general": ""}, {"aid": "15597", "name": "Edens Zero - 10", "kanji": "", "image": "https://cdn-eu.anidb.net/images/65/262163.jpg-thumb.jpg", "ep": "The Great Naked Escape", "desc": "", "extra": "", "general": ""}, {"aid": "15955", "name": "Idolish Seven: Third Beat! - 1", "kanji": "", "image": "https://cdn-eu.anidb.net/images/65/261889.jpg-thumb.jpg", "ep": "Clouds Covering the Stars", "desc": "", "extra": "", "general": ""}, {"aid": "15955", "name": "Idolish Seven: Third Beat! - 3", "kanji": "", "image": "https://cdn-eu.anidb.net/images/65/261889.jpg-thumb.jpg", "ep": "Rifts", "desc": "", "extra": "", "general": ""}, {"aid": "16612", "name": "Jueshi Wu Hun - 70", "kanji": "", "image": "https://cdn-eu.anidb.net/images/65/265245.jpg-thumb.jpg", "ep": "Episode 70", "desc": "", "extra": "", "general": ""}, {"aid": "16084", "name": "Mazica Party - 11", "kanji": "", "image": "https://cdn-eu.anidb.net/images/65/260471.jpg-thumb.jpg", "ep": "Episode 11", "desc": "", "extra": "", "general": ""}, {"aid": "15271", "name": "Nomad: Megalo Box 2 - 11", "kanji": "", "image": "https://cdn-eu.anidb.net/images/65/258240.jpg-thumb.jpg", "ep": "Cuando te quitas la armadura que no te podias quitar, brotan las semillas de la miseria y de la dicha", "desc": "", "extra": "", "general": ""}, {"aid": "69", "name": "One Piece - 978", "kanji": "", "image": "https://cdn-eu.anidb.net/images/65/224210.jpg-thumb.jpg", "ep": "The Worst Generation Charges In! The Battle of the Stormy Sea!", "desc": "", "extra": "", "general": ""}, {"aid": "16284", "name": "Pretty All Friends Selection - 2", "kanji": "", "image": "https://cdn-eu.anidb.net/images/65/261888.jpg-thumb.jpg", "ep": "Episode 2", "desc": "", "extra": "", "general": ""}, {"aid": "15708", "name": "Sayonara Watashi no Cramer - 11", "kanji": "", "image": "https://cdn-eu.anidb.net/images/65/255788.jpg-thumb.jpg", "ep": "The One Running Beside Us", "desc": "", "extra": "", "general": ""}, {"aid": "15779", "name": "Shadows House - 10", "kanji": "", "image": "https://cdn-eu.anidb.net/images/65/258223.jpg-thumb.jpg", "ep": "The Final Pair", "desc": "", "extra": "", "general": ""}, {"aid": "16382", "name": "Tai Yi Xian Mo Lu: Ling Fei Ji IV - 6", "kanji": "", "image": "https://cdn-eu.anidb.net/images/65/261417.jpg-thumb.jpg", "ep": "Episode 6", "desc": "", "extra": "", "general": ""}, {"aid": "15872", "name": "Tropical-Rouge! Precure - 16", "kanji": "", "image": "https://cdn-eu.anidb.net/images/65/255072.jpg-thumb.jpg", "ep": "The Witch`s Trap! Laura Was Captured!", "desc": "", "extra": "", "general": ""}, {"aid": "15774", "name": "Yuukoku no Moriarty (2021) - 11", "kanji": "", "image": "https://cdn-eu.anidb.net/images/65/256688.jpg-thumb.jpg", "ep": "The Two Criminals", "desc": "", "extra": "", "general": ""}]}}