{"update": "2022-02-17 11:30:00.359564", "calendar": {"2022-02-14": [{"aid": "15865", "name": "Sasaki to Miyano - 6", "kanji": "", "image": "https://cdn-eu.anidb.net/images/65/266980.jpg-thumb.jpg", "ep": "Feelings", "desc": "", "extra": "", "general": ""}, {"aid": "16825", "name": "Tribe Nine - 6", "kanji": "", "image": "https://cdn-eu.anidb.net/images/65/268259.jpg-thumb.jpg", "ep": "A Man`s Pride", "desc": "", "extra": "", "general": ""}, {"aid": "17057", "name": "Yami Shibai 10 - 6", "kanji": "", "image": "https://cdn-eu.anidb.net/images/65/267715.jpg-thumb.jpg", "ep": "Trash Drop-off", "desc": "", "extra": "", "general": ""}], "2022-02-15": [{"aid": "16497", "name": "Gensou Sangokushi: Tengen Reishinki - 6", "kanji": "", "image": "https://cdn-eu.anidb.net/images/65/268310.jpg-thumb.jpg", "ep": "Curse-Heart", "desc": "", "extra": "", "general": ""}, {"aid": "16103", "name": "Sabikui Bisco - 6", "kanji": "", "image": "https://cdn-eu.anidb.net/images/65/268260.jpg-thumb.jpg", "ep": "Companions and Prey", "desc": "", "extra": "", "general": ""}, {"aid": "16028", "name": "Tensai Ouji no Akaji Kokka Saisei Jutsu - 6", "kanji": "", "image": "https://cdn-eu.anidb.net/images/65/268261.jpg-thumb.jpg", "ep": "Holy Intrigue!", "desc": "", "extra": "", "general": ""}], "2022-02-16": [{"aid": "16950", "name": "Irodorimidori (2022) - 7", "kanji": "", "image": "https://cdn-eu.anidb.net/images/65/267433.jpg-thumb.jpg", "ep": "Episode 7", "desc": "", "extra": "", "general": ""}, {"aid": "15917", "name": "Koroshi Ai - 6", "kanji": "", "image": "https://cdn-eu.anidb.net/images/65/267053.jpg-thumb.jpg", "ep": "Dark Dream", "desc": "", "extra": "", "general": ""}, {"aid": "16071", "name": "Ore, Tsushima - S87", "kanji": "", "image": "https://cdn-eu.anidb.net/images/65/257465.jpg-thumb.jpg", "ep": "WEB Animation Episode 87", "desc": "", "extra": "", "general": ""}, {"aid": "17093", "name": "Tunshi Xingkong Zhuangzhi Lingyun - 10", "kanji": "", "image": "https://cdn-eu.anidb.net/images/65/268237.jpg-thumb.jpg", "ep": "Episode 10", "desc": "", "extra": "", "general": ""}, {"aid": "16592", "name": "Wan Sheng Jie 3 - 5", "kanji": "", "image": "https://cdn-eu.anidb.net/images/65/264600.jpg-thumb.jpg", "ep": "Episode 5", "desc": "", "extra": "", "general": ""}, {"aid": "16370", "name": "BanG Dream! Garupa Pico: Fever! - 20", "kanji": "", "image": "https://cdn-eu.anidb.net/images/65/265249.jpg-thumb.jpg", "ep": "Episode 20", "desc": "", "extra": "", "general": ""}, {"aid": "15418", "name": "Norimono Man: Mobile Land no Car-kun - 99", "kanji": "", "image": "https://cdn-eu.anidb.net/images/65/244754.jpg-thumb.jpg", "ep": "Episode 99", "desc": "", "extra": "", "general": ""}, {"aid": "17163", "name": "Qian Cong Shou - 6", "kanji": "", "image": "https://cdn-eu.anidb.net/images/65/269235.jpg-thumb.jpg", "ep": "Episode 06", "desc": "", "extra": "", "general": ""}, {"aid": "15596", "name": "Shaman King (2021) - 44", "kanji": "", "image": "https://cdn-eu.anidb.net/images/65/258069.jpg-thumb.jpg", "ep": "Speak Slowly", "desc": "", "extra": "", "general": ""}], "2022-02-18": [{"aid": "17106", "name": "Feng Qi Luoyang: Shen Ji Shaonian - 12", "kanji": "", "image": "https://cdn-eu.anidb.net/images/65/268548.jpg-thumb.jpg", "ep": "Episode 12", "desc": "", "extra": "", "general": ""}, {"aid": "16418", "name": "Goodbye, Don Glees!", "kanji": "", "image": "https://cdn-eu.anidb.net/images/65/264836.jpg-thumb.jpg", "ep": "Complete Movie", "desc": "", "extra": "", "general": ""}, {"aid": "15298", "name": "Ousama Ranking - 18", "kanji": "", "image": "https://cdn-eu.anidb.net/images/65/266134.jpg-thumb.jpg", "ep": "Episode 18", "desc": "", "extra": "", "general": ""}, {"aid": "15067", "name": "Pocket Monsters (2019) - 98", "kanji": "", "image": "https://cdn-eu.anidb.net/images/65/240961.jpg-thumb.jpg", "ep": "Episode 98", "desc": "", "extra": "", "general": ""}, {"aid": "15994", "name": "Shinkansen Henkei Robo Shinkalion Z the Animation - 37", "kanji": "", "image": "https://cdn-eu.anidb.net/images/65/259118.jpg-thumb.jpg", "ep": "Episode 37", "desc": "", "extra": "", "general": ""}, {"aid": "15943", "name": "Slow Loop - 7", "kanji": "", "image": "https://cdn-eu.anidb.net/images/65/267209.jpg-thumb.jpg", "ep": "Episode 7", "desc": "", "extra": "", "general": ""}, {"aid": "16077", "name": "Youkai Watch (2021) - 43", "kanji": "", "image": "https://cdn-eu.anidb.net/images/65/260077.jpg-thumb.jpg", "ep": "Episode 43", "desc": "", "extra": "", "general": ""}], "2022-02-19": [{"aid": "15827", "name": "Cue! - 7", "kanji": "", "image": "https://cdn-eu.anidb.net/images/65/267943.jpg-thumb.jpg", "ep": "Episode 7", "desc": "", "extra": "", "general": ""}, {"aid": "15680", "name": "Dosukoi Sushi Zumou - 47", "kanji": "", "image": "https://cdn-eu.anidb.net/images/65/259111.jpg-thumb.jpg", "ep": "Episode 47", "desc": "", "extra": "", "general": ""}, {"aid": "16559", "name": "Karakai Jouzu no Takagi-san 3 - 7", "kanji": "", "image": "https://cdn-eu.anidb.net/images/65/267424.jpg-thumb.jpg", "ep": "Episode 7", "desc": "", "extra": "", "general": ""}, {"aid": "16029", "name": "Shikkaku Mon no Saikyou Kenja - 7", "kanji": "", "image": "https://cdn-eu.anidb.net/images/65/267425.jpg-thumb.jpg", "ep": "Episode 7", "desc": "", "extra": "", "general": ""}, {"aid": "16367", "name": "Vanitas no Karte (2022) - 6", "kanji": "", "image": "https://cdn-eu.anidb.net/images/65/267436.jpg-thumb.jpg", "ep": "Episode 6", "desc": "", "extra": "", "general": ""}], "2022-02-20": [{"aid": "14820", "name": "Ani x Para - 14", "kanji": "", "image": "https://cdn-eu.anidb.net/images/65/244789.jpg-thumb.jpg", "ep": "Episode 14", "desc": "", "extra": "", "general": ""}, {"aid": "12661", "name": "Boruto: Naruto Next Generations - 237", "kanji": "", "image": "https://cdn-eu.anidb.net/images/65/258555.jpg-thumb.jpg", "ep": "The Mobile Fortress", "desc": "", "extra": "", "general": ""}, {"aid": "16502", "name": "Digimon Ghost Game - 19", "kanji": "", "image": "https://cdn-eu.anidb.net/images/65/264841.jpg-thumb.jpg", "ep": "Episode 19", "desc": "", "extra": "", "general": ""}, {"aid": "17004", "name": "Fanren Xiu Xian Chuan: Mo Dao Zhengfeng - 17", "kanji": "", "image": "https://cdn-eu.anidb.net/images/65/267236.jpg-thumb.jpg", "ep": "Episode 17", "desc": "", "extra": "", "general": ""}, {"aid": "16804", "name": "Genjitsu Shugi Yuusha no Oukoku Saikenki (2022) - 7", "kanji": "", "image": "https://cdn-eu.anidb.net/images/65/267431.jpg-thumb.jpg", "ep": "Episode 7", "desc": "", "extra": "", "general": ""}, {"aid": "16350", "name": "Lupin Sansei: Part 6 - 19", "kanji": "", "image": "https://cdn-eu.anidb.net/images/65/264565.jpg-thumb.jpg", "ep": "Fakes Attract Lies Part 2", "desc": "", "extra": "", "general": ""}, {"aid": "15901", "name": "Mewkledreamy Mix! - 45", "kanji": "", "image": "https://cdn-eu.anidb.net/images/65/259936.jpg-thumb.jpg", "ep": "Episode 45", "desc": "", "extra": "", "general": ""}, {"aid": "13733", "name": "PazuDora - 192", "kanji": "", "image": "https://cdn-eu.anidb.net/images/65/215470.jpg-thumb.jpg", "ep": "Episode 192", "desc": "", "extra": "", "general": ""}, {"aid": "16920", "name": "Ryman`s Club - 5", "kanji": "", "image": "https://cdn-eu.anidb.net/images/65/268900.jpg-thumb.jpg", "ep": "Episode 5", "desc": "", "extra": "", "general": ""}, {"aid": "1830", "name": "Sazae-san - 2624", "kanji": "", "image": "https://cdn-eu.anidb.net/images/65/73013.jpg-thumb.jpg", "ep": "Episode 2624", "desc": "", "extra": "", "general": ""}, {"aid": "16250", "name": "Sono Bisque Doll wa Koi o Suru - 7", "kanji": "", "image": "https://cdn-eu.anidb.net/images/65/269049.jpg-thumb.jpg", "ep": "Episode 7", "desc": "", "extra": "", "general": ""}, {"aid": "16581", "name": "Xing Chen Bian (2022) - 7", "kanji": "", "image": "https://cdn-eu.anidb.net/images/65/264553.jpg-thumb.jpg", "ep": "Episode 7", "desc": "", "extra": "", "general": ""}, {"aid": "17202", "name": "Zannen na Ikimono Jiten (2022) - 2", "kanji": "", "image": "https://cdn-eu.anidb.net/images/65/244805.jpg-thumb.jpg", "ep": "Episode 2", "desc": "", "extra": "", "general": ""}]}}