{"update": "2022-07-28 10:48:33.778424", "calendar": {"2022-07-25": [{"aid": "16495", "name": "Insect Land - 17", "kanji": "", "image": "https://cdn-eu.anidb.net/images/65/271605.jpg-thumb.jpg", "ep": "Episode 17", "desc": "", "extra": "", "general": ""}, {"aid": "16030", "name": "Tensei Kenja no Isekai Life: Daini no Shokugyou o Ete, Sekai Saikyou ni Narimashita - 5", "kanji": "", "image": "https://cdn-eu.anidb.net/images/65/268443.jpg-thumb.jpg", "ep": "That Cold Looked Troubling", "desc": "", "extra": "", "general": ""}, {"aid": "17208", "name": "Youkoso Jitsuryoku Shijou Shugi no Kyoushitsu e 2nd Season - 4", "kanji": "", "image": "https://cdn-eu.anidb.net/images/65/274564.jpg-thumb.jpg", "ep": "The Material Has to Be Created.", "desc": "", "extra": "", "general": ""}], "2022-07-26": [{"aid": "17511", "name": "Meng Qi Shi Shen: Huanxi Zhui Hun - 5", "kanji": "", "image": "https://cdn-eu.anidb.net/images/65/274967.jpg-thumb.jpg", "ep": "Don`t Worry! There`s Food!", "desc": "", "extra": "", "general": ""}, {"aid": "16296", "name": "Overlord IV - 4", "kanji": "", "image": "https://cdn-eu.anidb.net/images/65/267716.jpg-thumb.jpg", "ep": "The Ruler of Conspiracy", "desc": "", "extra": "", "general": ""}, {"aid": "15443", "name": "Wu Shen Zhuzai - 252", "kanji": "", "image": "https://cdn-eu.anidb.net/images/65/245005.jpg-thumb.jpg", "ep": "Episode 252", "desc": "", "extra": "", "general": ""}], "2022-07-27": [{"aid": "16389", "name": "Isekai Ojisan - 4", "kanji": "", "image": "https://cdn-eu.anidb.net/images/65/273638.jpg-thumb.jpg", "ep": "Episode 4", "desc": "", "extra": "", "general": ""}, {"aid": "15359", "name": "Made in Abyss: Retsujitsu no Ougonkyou - 4", "kanji": "", "image": "https://cdn-eu.anidb.net/images/65/271327.jpg-thumb.jpg", "ep": "Friend", "desc": "", "extra": "", "general": ""}, {"aid": "17077", "name": "Sasaki to Miyano: Koi ni Kizuku Mae no Chotto Shita Hanashi.", "kanji": "", "image": "https://cdn-eu.anidb.net/images/65/274285.jpg-thumb.jpg", "ep": "OAD", "desc": "", "extra": "", "general": ""}, {"aid": "15485", "name": "Tokyo Mew Mew New - 4", "kanji": "", "image": "https://cdn-eu.anidb.net/images/65/263202.jpg-thumb.jpg", "ep": "Who Doesn`t Want to Be Her? Our Last Member Is a Huge Star!", "desc": "", "extra": "", "general": ""}, {"aid": "17427", "name": "Warau Arsnotoria Sun! - 4", "kanji": "", "image": "https://cdn-eu.anidb.net/images/65/274212.jpg-thumb.jpg", "ep": "Ding Dong", "desc": "", "extra": "", "general": ""}, {"aid": "17438", "name": "Bang Dream! Morfonication - 1", "kanji": "", "image": "https://cdn-eu.anidb.net/images/65/275050.jpg-thumb.jpg", "ep": "Monica`s Summer Plan", "desc": "", "extra": "", "general": ""}, {"aid": "16104", "name": "Hataraku Maou-sama!! - 3", "kanji": "", "image": "https://cdn-eu.anidb.net/images/65/273683.jpg-thumb.jpg", "ep": "Episode 3", "desc": "", "extra": "", "general": ""}, {"aid": "16878", "name": "Shin Tennis no Ouji-sama: U-17 World Cup - 4", "kanji": "", "image": "https://cdn-eu.anidb.net/images/65/274370.jpg-thumb.jpg", "ep": "Prince vs Prince", "desc": "", "extra": "", "general": ""}, {"aid": "15726", "name": "Uchuu Nanchara Kotetsu-kun - 46", "kanji": "", "image": "https://cdn-eu.anidb.net/images/65/259341.jpg-thumb.jpg", "ep": "Episode 46", "desc": "", "extra": "", "general": ""}], "2022-07-29": [{"aid": "17172", "name": "Chimimo - 4", "kanji": "", "image": "https://cdn-eu.anidb.net/images/65/274706.jpg-thumb.jpg", "ep": "Episode 4", "desc": "", "extra": "", "general": ""}, {"aid": "16568", "name": "Jian Wang 3: Xia Gan Yi Dan Shen Jianxin Season 3 - 6", "kanji": "", "image": "https://cdn-eu.anidb.net/images/65/275360.jpg-thumb.jpg", "ep": "Episode 6", "desc": "", "extra": "", "general": ""}, {"aid": "16972", "name": "Ohiru no Shocker-san - 28", "kanji": "", "image": "https://cdn-eu.anidb.net/images/65/267432.jpg-thumb.jpg", "ep": "Episode 28", "desc": "", "extra": "", "general": ""}, {"aid": "15975", "name": "Soredemo Ayumu wa Yosetekuru - 4", "kanji": "", "image": "https://cdn-eu.anidb.net/images/65/274705.jpg-thumb.jpg", "ep": "Episode 4", "desc": "", "extra": "", "general": ""}, {"aid": "16412", "name": "Strike the Blood Final - 4", "kanji": "", "image": "https://cdn-eu.anidb.net/images/65/268312.jpg-thumb.jpg", "ep": "Return of the Dawn IV", "desc": "", "extra": "", "general": ""}, {"aid": "16281", "name": "Wanmei Shijie - 69", "kanji": "", "image": "https://cdn-eu.anidb.net/images/65/260334.jpg-thumb.jpg", "ep": "Episode 69", "desc": "", "extra": "", "general": ""}, {"aid": "16077", "name": "Youkai Watch (2021) - 66", "kanji": "", "image": "https://cdn-eu.anidb.net/images/65/260077.jpg-thumb.jpg", "ep": "Episode 66", "desc": "", "extra": "", "general": ""}], "2022-07-30": [{"aid": "11843", "name": "Bonobono (2016) - 319", "kanji": "", "image": "https://cdn-eu.anidb.net/images/65/210747.jpg-thumb.jpg", "ep": "Episode 319", "desc": "", "extra": "", "general": ""}, {"aid": "17150", "name": "Hoshi no Samidare - 4", "kanji": "", "image": "https://cdn-eu.anidb.net/images/65/271900.jpg-thumb.jpg", "ep": "Episode 4", "desc": "", "extra": "", "general": ""}, {"aid": "17006", "name": "Kami Kuzu Idol - 5", "kanji": "", "image": "https://cdn-eu.anidb.net/images/65/274366.jpg-thumb.jpg", "ep": "Episode 5", "desc": "", "extra": "", "general": ""}, {"aid": "17204", "name": "Kuro no Shoukanshi - 4", "kanji": "", "image": "https://cdn-eu.anidb.net/images/65/274092.jpg-thumb.jpg", "ep": "Episode 4", "desc": "", "extra": "", "general": ""}, {"aid": "17097", "name": "Lycoris Recoil - 5", "kanji": "", "image": "https://cdn-eu.anidb.net/images/65/273740.jpg-thumb.jpg", "ep": "Episode 5", "desc": "", "extra": "", "general": ""}, {"aid": "13070", "name": "Musashino! - 5", "kanji": "", "image": "https://cdn-eu.anidb.net/images/65/275512.jpg-thumb.jpg", "ep": "Episode 5", "desc": "", "extra": "", "general": ""}, {"aid": "16855", "name": "Shadowverse Flame - 18", "kanji": "", "image": "https://cdn-eu.anidb.net/images/65/268763.jpg-thumb.jpg", "ep": "My Rhythm Is the Heartbeat of a Devil!", "desc": "", "extra": "", "general": ""}, {"aid": "17118", "name": "Teppen!!!!!!!!!!!!!!! - 4", "kanji": "", "image": "https://cdn-eu.anidb.net/images/65/274909.jpg-thumb.jpg", "ep": "Episode 4", "desc": "", "extra": "", "general": ""}, {"aid": "17425", "name": "Zanting! Rang Wo Cha Gonglue - 12", "kanji": "", "image": "https://cdn-eu.anidb.net/images/65/273225.jpg-thumb.jpg", "ep": "Episode 12", "desc": "", "extra": "", "general": ""}], "2022-07-31": [{"aid": "16188", "name": "Cuckoo no Iinazuke - 14", "kanji": "", "image": "https://cdn-eu.anidb.net/images/65/268911.jpg-thumb.jpg", "ep": "Episode 14", "desc": "", "extra": "", "general": ""}, {"aid": "16502", "name": "Digimon Ghost Game - 36", "kanji": "", "image": "https://cdn-eu.anidb.net/images/65/264841.jpg-thumb.jpg", "ep": "Labyrinth of Grief", "desc": "", "extra": "", "general": ""}, {"aid": "17284", "name": "Engage Kiss - 5", "kanji": "", "image": "https://cdn-eu.anidb.net/images/65/274367.jpg-thumb.jpg", "ep": "Fleeting Scars", "desc": "", "extra": "", "general": ""}, {"aid": "17004", "name": "Fanren Xiu Xian Chuan: Mo Dao Zhengfeng - 40", "kanji": "", "image": "https://cdn-eu.anidb.net/images/65/267236.jpg-thumb.jpg", "ep": "Episode 40", "desc": "", "extra": "", "general": ""}, {"aid": "15971", "name": "Holo no Graffiti - 168", "kanji": "", "image": "https://cdn-eu.anidb.net/images/65/255285.jpg-thumb.jpg", "ep": "Episode 168", "desc": "", "extra": "", "general": ""}, {"aid": "16912", "name": "Kingdom (2022) - 17", "kanji": "", "image": "https://cdn-eu.anidb.net/images/65/271601.jpg-thumb.jpg", "ep": "Episode 17", "desc": "", "extra": "", "general": ""}, {"aid": "69", "name": "One Piece - 1027", "kanji": "", "image": "https://cdn-eu.anidb.net/images/65/224210.jpg-thumb.jpg", "ep": "Defend Luffy! Zoro and Law`s Sword Technique!", "desc": "", "extra": "", "general": ""}, {"aid": "17156", "name": "Prima Doll - 5", "kanji": "", "image": "https://cdn-eu.anidb.net/images/65/274093.jpg-thumb.jpg", "ep": "Episode 5", "desc": "", "extra": "", "general": ""}, {"aid": "14204", "name": "Renmei Kuugun Koukuu Mahou Ongakutai Luminous Witches - 5", "kanji": "", "image": "https://cdn-eu.anidb.net/images/65/273407.jpg-thumb.jpg", "ep": "Pure White Ribbon", "desc": "", "extra": "", "general": ""}, {"aid": "17361", "name": "Uta no Prince-sama: Maji Love Starish Tours - Tabi no Hajimari", "kanji": "", "image": "https://cdn-eu.anidb.net/images/65/272893.jpg-thumb.jpg", "ep": "TV Special", "desc": "", "extra": "", "general": ""}, {"aid": "16399", "name": "Waccha PriMagi! - 41", "kanji": "", "image": "https://cdn-eu.anidb.net/images/65/265139.jpg-thumb.jpg", "ep": "Episode 41", "desc": "", "extra": "", "general": ""}, {"aid": "17062", "name": "Yuu Gi Ou: Go Rush!! - 18", "kanji": "", "image": "https://cdn-eu.anidb.net/images/65/270526.jpg-thumb.jpg", "ep": "Episode 18", "desc": "", "extra": "", "general": ""}]}}