{"update": "2022-01-28 10:52:04.237871", "calendar": {"2022-01-24": [{"aid": "16177", "name": "Shingeki no Kyojin: The Final Season (2022) - 3", "kanji": "", "image": "https://cdn-eu.anidb.net/images/65/267124.jpg-thumb.jpg", "ep": "Two Brothers", "desc": "", "extra": "", "general": ""}, {"aid": "17057", "name": "Yami Shibai 10 - 3", "kanji": "", "image": "https://cdn-eu.anidb.net/images/65/267715.jpg-thumb.jpg", "ep": "The End of the Day", "desc": "", "extra": "", "general": ""}], "2022-01-25": [{"aid": "15608", "name": "Fushigi Dagashiya: Zenitendou - 48", "kanji": "", "image": "https://cdn-eu.anidb.net/images/65/259191.jpg-thumb.jpg", "ep": "Episode 48", "desc": "", "extra": "", "general": ""}, {"aid": "16972", "name": "Ohiru no Shocker-san - 3", "kanji": "", "image": "https://cdn-eu.anidb.net/images/65/267432.jpg-thumb.jpg", "ep": "Episode 3", "desc": "", "extra": "", "general": ""}, {"aid": "16103", "name": "Sabikui Bisco - 3", "kanji": "", "image": "https://cdn-eu.anidb.net/images/65/268260.jpg-thumb.jpg", "ep": "Tag Team", "desc": "", "extra": "", "general": ""}, {"aid": "16594", "name": "Zi Chuan - 7", "kanji": "", "image": "https://cdn-eu.anidb.net/images/65/264603.jpg-thumb.jpg", "ep": "Episode 7", "desc": "", "extra": "", "general": ""}], "2022-01-26": [{"aid": "16503", "name": "Hakozume: Kouban Joshi no Gyakushuu - 4", "kanji": "", "image": "https://cdn-eu.anidb.net/images/65/267379.jpg-thumb.jpg", "ep": "Dear Dog-sama / Runner`s High", "desc": "", "extra": "", "general": ""}, {"aid": "15578", "name": "Kenja no Deshi o Nanoru Kenja - 3", "kanji": "", "image": "https://cdn-eu.anidb.net/images/65/266975.jpg-thumb.jpg", "ep": "I`m... a Big Softie When It Comes to These Things", "desc": "", "extra": "", "general": ""}, {"aid": "16069", "name": "Leadale no Daichi nite - 4", "kanji": "", "image": "https://cdn-eu.anidb.net/images/65/269088.jpg-thumb.jpg", "ep": "A Son, a Fight, a Journey, and Bandits", "desc": "", "extra": "", "general": ""}, {"aid": "16071", "name": "Ore, Tsushima - S78", "kanji": "", "image": "https://cdn-eu.anidb.net/images/65/257465.jpg-thumb.jpg", "ep": "WEB Animation Episode 78", "desc": "", "extra": "", "general": ""}, {"aid": "17093", "name": "Tunshi Xingkong Zhuangzhi Lingyun - 6", "kanji": "", "image": "https://cdn-eu.anidb.net/images/65/268237.jpg-thumb.jpg", "ep": "Episode 6", "desc": "", "extra": "", "general": ""}, {"aid": "15726", "name": "Uchuu Nanchara Kotetsu-kun - 28", "kanji": "", "image": "https://cdn-eu.anidb.net/images/65/259341.jpg-thumb.jpg", "ep": "Episode 28", "desc": "", "extra": "", "general": ""}, {"aid": "16592", "name": "Wan Sheng Jie 3 - 2", "kanji": "", "image": "https://cdn-eu.anidb.net/images/65/264600.jpg-thumb.jpg", "ep": "Episode 2", "desc": "", "extra": "", "general": ""}], "2022-01-27": [{"aid": "15476", "name": "Maiko-san Chi no Makanai-san - 12", "kanji": "", "image": "https://cdn-eu.anidb.net/images/65/256041.jpg-thumb.jpg", "ep": "Dumplings for a Day Off / Sumire`s Day Off Part 1 / Sumire`s Day Off Part 2", "desc": "", "extra": "", "general": ""}, {"aid": "15969", "name": "Orient - 4", "kanji": "", "image": "https://cdn-eu.anidb.net/images/65/267112.jpg-thumb.jpg", "ep": "The Kosameda Band", "desc": "", "extra": "", "general": ""}, {"aid": "15980", "name": "Saiyuuki Reload Zeroin - 4", "kanji": "", "image": "https://cdn-eu.anidb.net/images/65/267318.jpg-thumb.jpg", "ep": "Options", "desc": "", "extra": "", "general": ""}, {"aid": "16928", "name": "Tokyo 24-ku - 4", "kanji": "", "image": "https://cdn-eu.anidb.net/images/65/267445.jpg-thumb.jpg", "ep": "Silver City", "desc": "", "extra": "", "general": ""}, {"aid": "16498", "name": "Wu Geng Ji (2021) - 29", "kanji": "", "image": "https://cdn-eu.anidb.net/images/65/263422.jpg-thumb.jpg", "ep": "Episode 29", "desc": "", "extra": "", "general": ""}, {"aid": "16276", "name": "Battle Spirits Mirage - 2", "kanji": "", "image": "https://cdn-eu.anidb.net/images/65/268256.jpg-thumb.jpg", "ep": "Episode 2", "desc": "", "extra": "", "general": ""}, {"aid": "16356", "name": "Dawang Raoming - 9", "kanji": "", "image": "https://cdn-eu.anidb.net/images/65/260931.jpg-thumb.jpg", "ep": "Chapter 9", "desc": "", "extra": "", "general": ""}, {"aid": "15298", "name": "Ousama Ranking - 15", "kanji": "", "image": "https://cdn-eu.anidb.net/images/65/266134.jpg-thumb.jpg", "ep": "The Order of the Underworld", "desc": "", "extra": "", "general": ""}, {"aid": "15067", "name": "Pocket Monsters (2019) - 95", "kanji": "", "image": "https://cdn-eu.anidb.net/images/65/240961.jpg-thumb.jpg", "ep": "Episode 95", "desc": "", "extra": "", "general": ""}, {"aid": "17151", "name": "Pocket Monsters: Kami to Yobareshi Arceus - 4", "kanji": "", "image": "https://cdn-eu.anidb.net/images/65/269094.jpg-thumb.jpg", "ep": "Episode 4", "desc": "", "extra": "", "general": ""}, {"aid": "15561", "name": "Shuumatsu no Harem - 4", "kanji": "", "image": "https://cdn-eu.anidb.net/images/65/265680.jpg-thumb.jpg", "ep": "Episode 4", "desc": "", "extra": "", "general": ""}, {"aid": "16281", "name": "Wanmei Shijie - 43", "kanji": "", "image": "https://cdn-eu.anidb.net/images/65/260334.jpg-thumb.jpg", "ep": "Episode 43", "desc": "", "extra": "", "general": ""}, {"aid": "16077", "name": "Youkai Watch (2021) - 40", "kanji": "", "image": "https://cdn-eu.anidb.net/images/65/260077.jpg-thumb.jpg", "ep": "Episode 40", "desc": "", "extra": "", "general": ""}], "2022-01-29": [{"aid": "15827", "name": "Cue! - 4", "kanji": "", "image": "https://cdn-eu.anidb.net/images/65/267943.jpg-thumb.jpg", "ep": "Episode 4", "desc": "", "extra": "", "general": ""}, {"aid": "15680", "name": "Dosukoi Sushi Zumou - 44", "kanji": "", "image": "https://cdn-eu.anidb.net/images/65/259111.jpg-thumb.jpg", "ep": "Episode 44", "desc": "", "extra": "", "general": ""}, {"aid": "15321", "name": "Dragon Quest: Dai no Daibouken (2020) - 67", "kanji": "", "image": "https://cdn-eu.anidb.net/images/65/251007.jpg-thumb.jpg", "ep": "Episode 67", "desc": "", "extra": "", "general": ""}, {"aid": "16141", "name": "Han`you no Yashahime: Sengoku Otogizoushi (2021) - 17", "kanji": "", "image": "https://cdn-eu.anidb.net/images/65/263723.jpg-thumb.jpg", "ep": "Episode 17", "desc": "", "extra": "", "general": ""}, {"aid": "266", "name": "Meitantei Conan - 1036", "kanji": "", "image": "https://cdn-eu.anidb.net/images/65/58683.jpg-thumb.jpg", "ep": "Episode 1036", "desc": "", "extra": "", "general": ""}, {"aid": "16029", "name": "Shikkaku Mon no Saikyou Kenja - 4", "kanji": "", "image": "https://cdn-eu.anidb.net/images/65/267425.jpg-thumb.jpg", "ep": "Episode 4", "desc": "", "extra": "", "general": ""}, {"aid": "16367", "name": "Vanitas no Karte (2022) - 3", "kanji": "", "image": "https://cdn-eu.anidb.net/images/65/267436.jpg-thumb.jpg", "ep": "Episode 3", "desc": "", "extra": "", "general": ""}], "2022-01-30": [{"aid": "16166", "name": "Akebi-chan no Sailor Fuku - 4", "kanji": "", "image": "https://cdn-eu.anidb.net/images/65/268117.jpg-thumb.jpg", "ep": "Episode 4", "desc": "", "extra": "", "general": ""}, {"aid": "12661", "name": "Boruto: Naruto Next Generations - 234", "kanji": "", "image": "https://cdn-eu.anidb.net/images/65/258555.jpg-thumb.jpg", "ep": "Episode 234", "desc": "", "extra": "", "general": ""}, {"aid": "16009", "name": "Duel Masters King! - 37", "kanji": "", "image": "https://cdn-eu.anidb.net/images/65/259997.jpg-thumb.jpg", "ep": "Episode 37", "desc": "", "extra": "", "general": ""}, {"aid": "17004", "name": "Fanren Xiu Xian Chuan: Mo Dao Zhengfeng - 14", "kanji": "", "image": "https://cdn-eu.anidb.net/images/65/267236.jpg-thumb.jpg", "ep": "Episode 14", "desc": "", "extra": "", "general": ""}, {"aid": "16804", "name": "Genjitsu Shugi Yuusha no Oukoku Saikenki (2022) - 4", "kanji": "", "image": "https://cdn-eu.anidb.net/images/65/267431.jpg-thumb.jpg", "ep": "Episode 4", "desc": "", "extra": "", "general": ""}, {"aid": "16425", "name": "Kaijin Kaihatsubu no Kuroitsu-san - 3", "kanji": "", "image": "https://cdn-eu.anidb.net/images/65/266937.jpg-thumb.jpg", "ep": "Episode 3", "desc": "", "extra": "", "general": ""}, {"aid": "16350", "name": "Lupin Sansei: Part 6 - 16", "kanji": "", "image": "https://cdn-eu.anidb.net/images/65/264565.jpg-thumb.jpg", "ep": "Episode 16", "desc": "", "extra": "", "general": ""}, {"aid": "15901", "name": "Mewkledreamy Mix! - 42", "kanji": "", "image": "https://cdn-eu.anidb.net/images/65/259936.jpg-thumb.jpg", "ep": "Episode 42", "desc": "", "extra": "", "general": ""}, {"aid": "16955", "name": "On Air Dekinai! - 4", "kanji": "", "image": "https://cdn-eu.anidb.net/images/65/268902.jpg-thumb.jpg", "ep": "Episode 4", "desc": "", "extra": "", "general": ""}, {"aid": "13733", "name": "PazuDora - 189", "kanji": "", "image": "https://cdn-eu.anidb.net/images/65/215470.jpg-thumb.jpg", "ep": "Episode 189", "desc": "", "extra": "", "general": ""}, {"aid": "14940", "name": "Sabiiro no Armor: Reimei - 4", "kanji": "", "image": "https://cdn-eu.anidb.net/images/65/264020.jpg-thumb.jpg", "ep": "Episode 4", "desc": "", "extra": "", "general": ""}, {"aid": "16250", "name": "Sono Bisque Doll wa Koi o Suru - 4", "kanji": "", "image": "https://cdn-eu.anidb.net/images/65/269049.jpg-thumb.jpg", "ep": "Does This Belong to Your Girlfriend?", "desc": "", "extra": "", "general": ""}, {"aid": "16399", "name": "Waccha PriMagi! - 16", "kanji": "", "image": "https://cdn-eu.anidb.net/images/65/265139.jpg-thumb.jpg", "ep": "Episode 16", "desc": "", "extra": "", "general": ""}, {"aid": "15017", "name": "Yuu Gi Ou: Sevens - 84", "kanji": "", "image": "https://cdn-eu.anidb.net/images/65/244805.jpg-thumb.jpg", "ep": "Episode 84", "desc": "", "extra": "", "general": ""}]}}