{"update": "2022-09-08 11:55:44.358285", "calendar": {"2022-08-08": [{"aid": "16495", "name": "Insect Land - 19", "kanji": "", "image": "https://cdn-eu.anidb.net/images/65/271605.jpg-thumb.jpg", "ep": "Episode 19", "desc": "", "extra": "", "general": ""}, {"aid": "17354", "name": "KJ File - 5", "kanji": "", "image": "https://cdn-eu.anidb.net/images/65/274371.jpg-thumb.jpg", "ep": "Episode 5", "desc": "", "extra": "", "general": ""}, {"aid": "17447", "name": "Shishang Zui Qiang Nan Zhujiao - 25", "kanji": "", "image": "https://cdn-eu.anidb.net/images/65/273635.jpg-thumb.jpg", "ep": "Episode 25", "desc": "", "extra": "", "general": ""}, {"aid": "16030", "name": "Tensei Kenja no Isekai Life: Daini no Shokugyou o Ete, Sekai Saikyou ni Narimashita - 7", "kanji": "", "image": "https://cdn-eu.anidb.net/images/65/268443.jpg-thumb.jpg", "ep": "Assassins in Pursuit", "desc": "", "extra": "", "general": ""}, {"aid": "16397", "name": "Wushang Shen Di Di Er Ji - 130", "kanji": "", "image": "https://cdn-eu.anidb.net/images/65/261621.jpg-thumb.jpg", "ep": "Episode 130", "desc": "", "extra": "", "general": ""}, {"aid": "17208", "name": "Youkoso Jitsuryoku Shijou Shugi no Kyoushitsu e 2nd Season - 6", "kanji": "", "image": "https://cdn-eu.anidb.net/images/65/274564.jpg-thumb.jpg", "ep": "Adversity Is the First Path to Truth.", "desc": "", "extra": "", "general": ""}], "2022-08-09": [{"aid": "14639", "name": "Ling Jian Zun - 304", "kanji": "", "image": "https://cdn-eu.anidb.net/images/65/229827.jpg-thumb.jpg", "ep": "Episode 304", "desc": "", "extra": "", "general": ""}, {"aid": "17275", "name": "Orient (2022) - 5", "kanji": "", "image": "https://cdn-eu.anidb.net/images/65/274064.jpg-thumb.jpg", "ep": "Memories of Stone", "desc": "", "extra": "", "general": ""}, {"aid": "16296", "name": "Overlord IV - S6", "kanji": "", "image": "https://cdn-eu.anidb.net/images/65/267716.jpg-thumb.jpg", "ep": "Ple-Ple-Pleiades 4: Ple 4 Ch 6 &quot;Alexander&quot;", "desc": "", "extra": "", "general": ""}, {"aid": "15443", "name": "Wu Shen Zhuzai - 256", "kanji": "", "image": "https://cdn-eu.anidb.net/images/65/245005.jpg-thumb.jpg", "ep": "Episode 256", "desc": "", "extra": "", "general": ""}, {"aid": "16594", "name": "Zi Chuan - 36", "kanji": "", "image": "https://cdn-eu.anidb.net/images/65/264603.jpg-thumb.jpg", "ep": "Episode 36", "desc": "", "extra": "", "general": ""}], "2022-08-10": [{"aid": "15749", "name": "Jashin-chan Dropkick X - 6", "kanji": "", "image": "https://cdn-eu.anidb.net/images/65/272775.jpg-thumb.jpg", "ep": "Gilding Kamuy: Kushiro", "desc": "", "extra": "", "general": ""}, {"aid": "17555", "name": "Kao Ni La! Zhanshen Xitong - 4", "kanji": "", "image": "https://cdn-eu.anidb.net/images/65/275831.jpg-thumb.jpg", "ep": "Big Jerk An Lin", "desc": "", "extra": "", "general": ""}, {"aid": "16457", "name": "Mamahaha no Tsurego ga Motokano Datta - 6", "kanji": "", "image": "https://cdn-eu.anidb.net/images/65/274369.jpg-thumb.jpg", "ep": "The Former Couple Goes Head-to-Head &quot;Do You Think I`m Stupid?!&quot;", "desc": "", "extra": "", "general": ""}, {"aid": "17058", "name": "Shaonian Bai Ma Zui Chun Feng - 4", "kanji": "", "image": "https://cdn-eu.anidb.net/images/65/267760.jpg-thumb.jpg", "ep": "Episode 4", "desc": "", "extra": "", "general": ""}, {"aid": "16937", "name": "Shine Post - 5", "kanji": "", "image": "https://cdn-eu.anidb.net/images/65/272825.jpg-thumb.jpg", "ep": "`Headstrong` Rio Seibu", "desc": "", "extra": "", "general": ""}, {"aid": "17093", "name": "Tunshi Xingkong Zhuangzhi Lingyun - 22", "kanji": "", "image": "https://cdn-eu.anidb.net/images/65/268237.jpg-thumb.jpg", "ep": "Episode 22", "desc": "", "extra": "", "general": ""}, {"aid": "17427", "name": "Warau Arsnotoria Sun! - 6", "kanji": "", "image": "https://cdn-eu.anidb.net/images/65/274212.jpg-thumb.jpg", "ep": "Shh-", "desc": "", "extra": "", "general": ""}, {"aid": "17333", "name": "Xinghe Zhizun Di Er Ji - 35", "kanji": "", "image": "https://cdn-eu.anidb.net/images/65/272304.jpg-thumb.jpg", "ep": "Episode 35", "desc": "", "extra": "", "general": ""}, {"aid": "16619", "name": "Yi Nian Yong Heng: Chuan Cheng Pian - 6", "kanji": "", "image": "https://cdn-eu.anidb.net/images/65/264851.jpg-thumb.jpg", "ep": "Episode 6", "desc": "", "extra": "", "general": ""}, {"aid": "17336", "name": "Yoru wa Neko to Issho - 3", "kanji": "", "image": "https://cdn-eu.anidb.net/images/65/275918.jpg-thumb.jpg", "ep": "A Cat That Tends to Drop Things", "desc": "", "extra": "", "general": ""}], "2022-08-11": [{"aid": "17595", "name": "Jun You Yun - 18", "kanji": "", "image": "https://cdn-eu.anidb.net/images/65/276790.jpg-thumb.jpg", "ep": "Shell of the Immortal", "desc": "", "extra": "", "general": ""}, {"aid": "17443", "name": "Sekai no Owari ni Shiba Inu to - 6", "kanji": "", "image": "https://cdn-eu.anidb.net/images/65/273558.jpg-thumb.jpg", "ep": "Nonconformist Gene / The Miracle of the Spring / Reconsidering Urashima", "desc": "", "extra": "", "general": ""}, {"aid": "17350", "name": "Shen Yin Wangzuo (2022) - 18", "kanji": "", "image": "https://cdn-eu.anidb.net/images/65/272719.jpg-thumb.jpg", "ep": "Episode 18", "desc": "", "extra": "", "general": ""}, {"aid": "15726", "name": "Uchuu Nanchara Kotetsu-kun - 48", "kanji": "", "image": "https://cdn-eu.anidb.net/images/65/259341.jpg-thumb.jpg", "ep": "Episode 48", "desc": "", "extra": "", "general": ""}, {"aid": "16630", "name": "Wo Qi Ku Liao Baiwan Xiulian Zhe - 106", "kanji": "", "image": "https://cdn-eu.anidb.net/images/65/264920.jpg-thumb.jpg", "ep": "Episode 106", "desc": "", "extra": "", "general": ""}, {"aid": "17336", "name": "Yoru wa Neko to Issho - 4", "kanji": "", "image": "https://cdn-eu.anidb.net/images/65/275918.jpg-thumb.jpg", "ep": "Cat Grooming Hurts", "desc": "", "extra": "", "general": ""}], "2022-08-12": [{"aid": "17278", "name": "Bucchigire! - S6", "kanji": "", "image": "https://cdn-eu.anidb.net/images/65/271777.jpg-thumb.jpg", "ep": "Mini Anime #6", "desc": "", "extra": "", "general": ""}, {"aid": "17172", "name": "Chimimo - 6", "kanji": "", "image": "https://cdn-eu.anidb.net/images/65/274706.jpg-thumb.jpg", "ep": "Hell Matter / Joyful Hell", "desc": "", "extra": "", "general": ""}, {"aid": "16620", "name": "Hei Men - 4", "kanji": "", "image": "https://cdn-eu.anidb.net/images/65/264902.jpg-thumb.jpg", "ep": "Episode 4", "desc": "", "extra": "", "general": ""}, {"aid": "14639", "name": "Ling Jian Zun - 305", "kanji": "", "image": "https://cdn-eu.anidb.net/images/65/229827.jpg-thumb.jpg", "ep": "Episode 305", "desc": "", "extra": "", "general": ""}, {"aid": "17450", "name": "Obey Me! (2022) - 3", "kanji": "", "image": "https://cdn-eu.anidb.net/images/65/273686.jpg-thumb.jpg", "ep": "The Long Awaited Ruri-chan Viewing Party", "desc": "", "extra": "", "general": ""}, {"aid": "15975", "name": "Soredemo Ayumu wa Yosetekuru - 6", "kanji": "", "image": "https://cdn-eu.anidb.net/images/65/274705.jpg-thumb.jpg", "ep": "I Want to Get It from You, Senpai", "desc": "", "extra": "", "general": ""}, {"aid": "16281", "name": "Wanmei Shijie - 71", "kanji": "", "image": "https://cdn-eu.anidb.net/images/65/260334.jpg-thumb.jpg", "ep": "Episode 71", "desc": "", "extra": "", "general": ""}, {"aid": "16971", "name": "Yofukashi no Uta - 6", "kanji": "", "image": "https://cdn-eu.anidb.net/images/65/272827.jpg-thumb.jpg", "ep": "Might as Well Have Fun", "desc": "", "extra": "", "general": ""}, {"aid": "16077", "name": "Youkai Watch (2021) - 68", "kanji": "", "image": "https://cdn-eu.anidb.net/images/65/260077.jpg-thumb.jpg", "ep": "Episode 68", "desc": "", "extra": "", "general": ""}], "2022-08-13": [{"aid": "15321", "name": "Dragon Quest: Dai no Daibouken (2020) - 90", "kanji": "", "image": "https://cdn-eu.anidb.net/images/65/251007.jpg-thumb.jpg", "ep": "Myst and Kill", "desc": "", "extra": "", "general": ""}, {"aid": "17357", "name": "Iii Icecrin 2 - 7", "kanji": "", "image": "https://cdn-eu.anidb.net/images/65/272816.jpg-thumb.jpg", "ep": "Episode 7", "desc": "", "extra": "", "general": ""}, {"aid": "15743", "name": "Kanojo, Okarishimasu (2022) - 7", "kanji": "", "image": "https://cdn-eu.anidb.net/images/65/274032.jpg-thumb.jpg", "ep": "Ex and Girlfriend", "desc": "", "extra": "", "general": ""}, {"aid": "16527", "name": "Love All Play - 19", "kanji": "", "image": "https://cdn-eu.anidb.net/images/65/271606.jpg-thumb.jpg", "ep": "Light Breeze", "desc": "", "extra": "", "general": ""}, {"aid": "266", "name": "Meitantei Conan - 1054", "kanji": "", "image": "https://cdn-eu.anidb.net/images/65/58683.jpg-thumb.jpg", "ep": "The Spark That Fell on the Ranch (Part 2)", "desc": "", "extra": "", "general": ""}, {"aid": "17014", "name": "Ninjala (2022) - 32", "kanji": "", "image": "https://cdn-eu.anidb.net/images/65/269048.jpg-thumb.jpg", "ep": "Van - Burning Ninja Spirit", "desc": "", "extra": "", "general": ""}, {"aid": "16629", "name": "Shadows House 2nd Season - 6", "kanji": "", "image": "https://cdn-eu.anidb.net/images/65/273426.jpg-thumb.jpg", "ep": "Night Sky", "desc": "", "extra": "", "general": ""}, {"aid": "17534", "name": "Shen Lan Qi Yu Wushuang Zhu - 6", "kanji": "", "image": "https://cdn-eu.anidb.net/images/65/275592.jpg-thumb.jpg", "ep": "Episode 6", "desc": "", "extra": "", "general": ""}, {"aid": "17118", "name": "Teppen!!!!!!!!!!!!!!! - 7", "kanji": "", "image": "https://cdn-eu.anidb.net/images/65/274909.jpg-thumb.jpg", "ep": "The Mail-Order Chapter", "desc": "", "extra": "", "general": ""}, {"aid": "16988", "name": "Yao Shen Ji 5 - 85", "kanji": "", "image": "https://cdn-eu.anidb.net/images/65/267191.jpg-thumb.jpg", "ep": "Episode 85", "desc": "", "extra": "", "general": ""}, {"aid": "17541", "name": "Zhan Qiannian - 5", "kanji": "", "image": "https://cdn-eu.anidb.net/images/65/275587.jpg-thumb.jpg", "ep": "Episode 5", "desc": "", "extra": "", "general": ""}], "2022-08-14": [{"aid": "17232", "name": "Cap Kakumei Bottleman DX - 20", "kanji": "", "image": "https://cdn-eu.anidb.net/images/65/271583.jpg-thumb.jpg", "ep": "I Am the Rulebook! Ijuin Shiman", "desc": "", "extra": "", "general": ""}, {"aid": "16953", "name": "Delicious Party Precure - 23", "kanji": "", "image": "https://cdn-eu.anidb.net/images/65/268599.jpg-thumb.jpg", "ep": "Is Kokone Selfish? Unforgettable Doughnut Holes.", "desc": "", "extra": "", "general": ""}, {"aid": "17052", "name": "Dou Po Cangqiong Nian Fan - 5", "kanji": "", "image": "https://cdn-eu.anidb.net/images/65/275779.jpg-thumb.jpg", "ep": "Episode 5", "desc": "", "extra": "", "general": ""}, {"aid": "17189", "name": "Extreme Hearts - 6", "kanji": "", "image": "https://cdn-eu.anidb.net/images/65/274532.jpg-thumb.jpg", "ep": "The Sword of the Heart", "desc": "", "extra": "", "general": ""}, {"aid": "17004", "name": "Fanren Xiu Xian Chuan: Mo Dao Zhengfeng - 42", "kanji": "", "image": "https://cdn-eu.anidb.net/images/65/276716.jpg-thumb.jpg", "ep": "Episode 42", "desc": "", "extra": "", "general": ""}, {"aid": "15971", "name": "Holo no Graffiti - 170", "kanji": "", "image": "https://cdn-eu.anidb.net/images/65/255285.jpg-thumb.jpg", "ep": "Typhoons Ruin Trip", "desc": "", "extra": "", "general": ""}, {"aid": "16612", "name": "Jueshi Wu Hun - 192", "kanji": "", "image": "https://cdn-eu.anidb.net/images/65/265245.jpg-thumb.jpg", "ep": "Episode 192", "desc": "", "extra": "", "general": ""}, {"aid": "17484", "name": "Knights of the Zodiac: Saint Seiya - Battle for Sanctuary - 4", "kanji": "", "image": "https://cdn-eu.anidb.net/images/65/274466.jpg-thumb.jpg", "ep": "Cold Hearted", "desc": "", "extra": "", "general": ""}, {"aid": "69", "name": "One Piece - 1029", "kanji": "", "image": "https://cdn-eu.anidb.net/images/65/224210.jpg-thumb.jpg", "ep": "A Faint Memory! Luffy and Red-Haired`s Daughter Uta!", "desc": "", "extra": "", "general": ""}, {"aid": "17156", "name": "Prima Doll - 7", "kanji": "", "image": "https://cdn-eu.anidb.net/images/65/274093.jpg-thumb.jpg", "ep": "Dreamlike Days", "desc": "", "extra": "", "general": ""}, {"aid": "14204", "name": "Renmei Kuugun Koukuu Mahou Ongakutai Luminous Witches - S2", "kanji": "", "image": "https://cdn-eu.anidb.net/images/65/273407.jpg-thumb.jpg", "ep": "First Half Retrospective Special", "desc": "", "extra": "", "general": ""}, {"aid": "17443", "name": "Sekai no Owari ni Shiba Inu to - 8", "kanji": "", "image": "https://cdn-eu.anidb.net/images/65/273558.jpg-thumb.jpg", "ep": "Under the Stars / The Dark Side / The Little Mermaid", "desc": "", "extra": "", "general": ""}, {"aid": "15206", "name": "Utawarerumono: Futari no Hakuoro - 8", "kanji": "", "image": "https://cdn-eu.anidb.net/images/65/272356.jpg-thumb.jpg", "ep": "Return", "desc": "", "extra": "", "general": ""}, {"aid": "16630", "name": "Wo Qi Ku Liao Baiwan Xiulian Zhe - 107", "kanji": "", "image": "https://cdn-eu.anidb.net/images/65/264920.jpg-thumb.jpg", "ep": "Episode 107", "desc": "", "extra": "", "general": ""}, {"aid": "17554", "name": "Xing Yuan Zhi Zhu - 8", "kanji": "", "image": "https://cdn-eu.anidb.net/images/65/275830.jpg-thumb.jpg", "ep": "Life in Ancestral Land", "desc": "", "extra": "", "general": ""}, {"aid": "17437", "name": "Xiong Bing Lian 3: Leiting Wan Jun - 14", "kanji": "", "image": "https://cdn-eu.anidb.net/images/65/273425.jpg-thumb.jpg", "ep": "Episode 14", "desc": "", "extra": "", "general": ""}, {"aid": "17207", "name": "Yurei Deco - 7", "kanji": "", "image": "https://cdn-eu.anidb.net/images/65/273637.jpg-thumb.jpg", "ep": "The Inhuman Cart", "desc": "", "extra": "", "general": ""}, {"aid": "17062", "name": "Yuu Gi Ou: Go Rush!! - 20", "kanji": "", "image": "https://cdn-eu.anidb.net/images/65/270526.jpg-thumb.jpg", "ep": "Goha Yuuna", "desc": "", "extra": "", "general": ""}]}}